dischub/__init__.py
dischub/main.py
dischub-2.1.1.dist-info/METADATA
dischub-2.1.1.dist-info/WHEEL
dischub-2.1.1.dist-info/top_level.txt
dischub-2.1.1.dist-info/RECORD
