Metadata-Version: 2.1
Name: dischub
Version: 2.1.1
Summary: A Python SDK to initiate online payment to the Dischub API
Home-page: https://softwarez.co.zw
Author: SoftwareZ
Author-email: support@softwarez.co.zw
License: MIT
Classifier: Programming Language :: Python :: 3
Classifier: License :: OSI Approved :: MIT License
Classifier: Operating System :: OS Independent
Requires-Python: >=3.6
Requires-Dist: requests
